{
    "type": "FeatureCollection",
    "crs": {
        "type": "name",
        "properties": {
            "name": "EPSG:4326"
        }
    },
    "features": [
        {
            "type": "Feature",
            "geometry": {
                "type": "Point",
                "coordinates": [
                    19.254,
                    47.524
                ]
            },
            "properties": {
                "name": "Tengerszem teniszke",
                "description": "Tengerszem utcai teniszközpont"
            }
        },
        {
            "type": "Feature",
            "geometry": {
                "type": "Point",
                "coordinates": [
                    19.9387,
                    47.732
                ]
            },
            "properties": {
                "name": "Mitchel/Pajot CI-Linwood: 98-08-0554-P",
                "description": "43.732, -83.9387"
            }
        }
    ]
}